ouroboros/Video.py
ouroboros/__init__.py
product_ouroboros-1.0.0.dist-info/DESCRIPTION.rst
product_ouroboros-1.0.0.dist-info/METADATA
product_ouroboros-1.0.0.dist-info/RECORD
product_ouroboros-1.0.0.dist-info/WHEEL
product_ouroboros-1.0.0.dist-info/metadata.json
product_ouroboros-1.0.0.dist-info/top_level.txt
