Metadata-Version: 2.0
Name: product-ouroboros
Version: 1.0.0
Summary: A library for simple video editing
Home-page: https://github.umn.edu/sebra006/ouroboros
Author: Product Lab
Author-email: sebra006@umn.edu
License: MIT
Keywords: simple video editing
Platform: UNKNOWN
Classifier: Development Status :: 3 - Alpha
Classifier: Intended Audience :: Education
Classifier: Topic :: Multimedia :: Video
Classifier: License :: OSI Approved :: MIT License
Classifier: Programming Language :: Python :: 3
Classifier: Programming Language :: Python :: 3.3
Classifier: Programming Language :: Python :: 3.4
Classifier: Programming Language :: Python :: 3.5
Requires-Dist: moviepy
Requires-Dist: pygame
